README.rst
setup.py
emqxlwm2m/__init__.py
emqxlwm2m/__main__.py
emqxlwm2m/cmd2loop.py
emqxlwm2m/codegen.py
emqxlwm2m/history.py
emqxlwm2m/loadobjects.py
emqxlwm2m/lwm2m.py
emqxlwm2m/parsers.py
emqxlwm2m/utils.py
emqxlwm2m.egg-info/PKG-INFO
emqxlwm2m.egg-info/SOURCES.txt
emqxlwm2m.egg-info/dependency_links.txt
emqxlwm2m.egg-info/requires.txt
emqxlwm2m.egg-info/top_level.txt
emqxlwm2m/engines/__init__.py
emqxlwm2m/engines/async_emqx.py
emqxlwm2m/engines/emqx.py
emqxlwm2m/oma/LWM2M.xsd
emqxlwm2m/oma/LWM2M_Access_Control-v1_0_1.xml
emqxlwm2m/oma/LWM2M_Connectivity_Statistics-v1_0_1.xml
emqxlwm2m/oma/LWM2M_Device-v1_0_1.xml
emqxlwm2m/oma/LWM2M_Firmware_Update-v1_0_1.xml
emqxlwm2m/oma/LWM2M_Location-v1_0.xml
emqxlwm2m/oma/LWM2M_Security-v1_0.xml
emqxlwm2m/oma/LWM2M_Server-v1_0.xml
emqxlwm2m/oma/__init__.py
emqxlwm2m/oma/connectivity_statistics_7.py
emqxlwm2m/oma/device_3.py
emqxlwm2m/oma/firmware_update_5.py
emqxlwm2m/oma/location_6.py
emqxlwm2m/oma/lwm2m_access_control_2.py
emqxlwm2m/oma/lwm2m_security_0.py
emqxlwm2m/oma/lwm2m_server_1.py