Metadata-Version: 1.1
Name: emqxlwm2m
Version: 0.6.0
Summary: A Python interface to the EMQx LwM2M plugin
Home-page: https://github.com/Penlect/emqxlwm2m
Author: Daniel Andersson
Author-email: daniel.4ndersson@gmail.com
License: MIT
Keywords: emqx lwm2m emqx-lwm2m
Platform: UNKNOWN
Classifier: Development Status :: 4 - Beta
Classifier: Environment :: Console
Classifier: Intended Audience :: Developers
Classifier: License :: OSI Approved :: MIT License
Classifier: Natural Language :: English
Classifier: Operating System :: POSIX :: Linux
Classifier: Operating System :: MacOS
Classifier: Operating System :: Microsoft :: Windows :: Windows 10
Classifier: Programming Language :: Python :: 3
Classifier: Programming Language :: Python :: Implementation :: CPython
